behave_db/__init__.py
behave_db/environment.py
behave_db/steps/__init__.py
behave_db/steps/basic.py
behave_db/utils.py
behave_db-0.0.6.dist-info/LICENSE
behave_db-0.0.6.dist-info/WHEEL
behave_db-0.0.6.dist-info/METADATA
behave_db-0.0.6.dist-info/RECORD
